{
    "source": "প্রথম আলো",
    "articles": [
        {
            "title": "রেকর্ড উষ্ণ জুলাইয়ের ধারা থামলেও শঙ্কা বাড়ছে | প্রথম আলো",
            "time": "2025-08-07T07:20:41",
            "imgUrl": "https://media.prothomalo.com/prothomalo-bangla%2F2025-08-07%2Fdy0blqfq%2FHot-July-1.jpg?rect=0%2C512%2C7230%2C3796&w=1200&ar=40%3A21&auto=format%2Ccompress&ogImage=true&mode=crop&overlay=https%3A%2F%2Fmedia.prothomalo.com%2Fprothomalo-bangla%2F2024-09-22%2F5lwyn5je%2Fdefaultog.jpg&overlay_position=bottom&overlay_width_pct=1",
            "body": "<html><body><div><div class=\"story-element story-element-text\"><div><p>গত মাসে উপসাগরীয় অঞ্চল, ইরাক এবং প্রথমবারের মতো তুরস্কে তাপমাত্রা ৫০ ডিগ্রি সেলসিয়াস ছাড়িয়ে গেছে। অন্যদিকে চীন ও পাকিস্তানে অতিবৃষ্টিতে শত শত মানুষের মৃত্যু হয়েছে।</p><p>স্পেনের এক সরকারি সংস্থা জানিয়েছে, দেশটিতে জুলাই মাসে তাপপ্রবাহের কারণে এক হাজারের বেশি মানুষের মৃত্যুর ঘটনা ঘটেছে। তবে তা গত বছরের একই সময়ের তুলনায় অর্ধেক।</p><p>তাপমাত্রা বৃদ্ধির মূল কারণ কার্বন ডাই–অক্সাইড বেড়ে যাওয়া। আর বিজ্ঞানীরা চিহ্নিত করেছেন জীবাশ্ম জ্বালানি—তেল, কয়লা ও গ্যাস ব্যবহারের কারণে কার্বন ডাই–অক্সাইডের মাত্রা বেড়ে যাচ্ছে।</p><p>বুয়োনতেম্পো সতর্ক করে বলেন, ‘যদি আমরা দ্রুত বায়ুমণ্ডলে গ্রিনহাউস গ্যাসের ঘনত্ব স্থিতিশীল করতে না পারি, তাহলে শুধু নতুন রেকর্ড নয়, পরিণতি আরও খারাপ হবে।’</p></div></div></div></body></html>"
        },
        {
            "title": "বিশ্বে চোখজুড়ানো ১০ গ্রন্থাগার | প্রথম আলো",
            "time": "2025-08-07T07:14:56",
            "imgUrl": "https://media.prothomalo.com/prothomalo-bangla%2F2025-08-07%2Fhp8dt2of%2Fa6940043-a281-4563-bf23-b89ae6f63731.jfif?rect=0%2C114%2C1600%2C840&w=1200&ar=40%3A21&auto=format%2Ccompress&ogImage=true&mode=crop&overlay=https%3A%2F%2Fmedia.prothomalo.com%2Fprothomalo-bangla%2F2024-09-22%2F5lwyn5je%2Fdefaultog.jpg&overlay_position=bottom&overlay_width_pct=1",
            "body": "<html><body><div><div class=\"story-element story-element-text\"><div><p>দুনিয়ায় কিছু গ্রন্থাগার আছে, যেগুলো শুধু বই ধার নেওয়ার জায়গা নয়; এগুলো এমন জায়গা, যেখানে লুকিয়ে আছে ইতিহাস, স্থাপত্য আর গল্পের বাইরের গল্প। ওয়ান থাউজেন্ড লাইব্রেরি ২০২৫ সালে বিশ্বের সবচেয়ে সুন্দর গ্রন্থাগারগুলোর একটি তালিকা তৈরি করেছে। অনলাইনে ভোটাভুটির ভিত্তিতে তালিকাটি করেছে তারা। প্রায় দুই লাখ মানুষ এ ভোটাভুটিতে অংশ নেন।</p><p> ওয়ান থাউজেন্ড লাইব্রেরি অ্যাওয়ার্ডস নামের সংগঠনটি একসময় একটা ছোট ব্লগ ছিল। কিন্তু এখন এটি বিশ্বজুড়ে বইপ্রেমীদের একটি বড় সংগঠন হিসেবে কাজ করছে। সংগঠনটির তালিকায় স্থান পাওয়া ১০টি নান্দনিক গ্রন্থাগার সম্পর্কে জেনে নেওয়া যাক।</p></div></div></div></body></html>"
        },
        {
            "title": "জুলাই ঘোষণাপত্র, বিশ্ব এআই সম্মেলন, পার্পল লাইন কী, জেনে নিন | প্রথম আলো",
            "time": "2025-08-07T07:11:28",
            "imgUrl": "https://media.prothomalo.com/prothomalo-bangla%2F2025-06-06%2Fxkjena33%2Flaw-5.png?rect=0%2C0%2C624%2C328&w=1200&ar=40%3A21&auto=format%2Ccompress&ogImage=true&mode=crop&overlay=https%3A%2F%2Fmedia.prothomalo.com%2Fprothomalo-bangla%2F2025-08-04%2F7ofy5i1p%2FWithout-Documents-Technology-Chakri-bakri.png&overlay_position=bottom&overlay_width_pct=1",
            "body": "<html><body><div><div class=\"story-element story-element-text\"><div><p><strong>৭. বাংলাদেশের একমাত্র ‘স্কিন ব্যাংক’ কোথায় অবস্থিত?</strong></p><p>ক. ঢাকা মেডিকেল কলেজ হাসপাতাল</p><p>খ. বারডেম হাসপাতাল</p><p>গ. জাতীয় বার্ন ও প্লাস্টিক সার্জারি ইনস্টিটিউট</p><p>ঘ. বাংলাদেশ মেডিকেল বিশ্ববিদ্যালয়</p><p>উত্তর: গ. জাতীয় বার্ন ও প্লাস্টিক সার্জারি ইনস্টিটিউট</p><p><strong>৮. ‘জাতীয় বহুমাত্রিক দারিদ্র্য সূচক (এমপিআই-২০২৫)’ অনুযায়ী, সবচেয়ে বহুমাত্রিক দারিদ্র্য রয়েছে কোন বিভাগে?</strong></p><p>ক. রংপুর</p><p>খ. ঢাকা</p><p>গ. বরিশাল</p><p>ঘ. সিলেট</p><p>উত্তর: ঘ. সিলেট</p><p>(দেশে বহুমাত্রিক দারিদ্র্যের হার ২৪.০৫ শতাংশ)</p><p><strong>৯. বাংলাদেশের চলচ্চিত্র ইতিহাসে প্রথম অনুদানপ্রাপ্ত সিনেমা—</strong></p><p>ক. এমিলের গোয়েন্দা বাহিনী</p><p>খ. মুক্তির গান</p><p>গ. ছুটির ঘণ্টা</p><p>ঘ. সূর্যদীঘল বাড়ি</p><p>উত্তর: ঘ. সূর্যদীঘল বাড়ি</p></div></div></div></body></html>"
        },
        {
            "title": "১৭ প্রতিষ্ঠানকে পুরস্কৃত করল ভিসা | প্রথম আলো",
            "time": "2025-08-07T07:00:00",
            "imgUrl": "https://media.prothomalo.com/prothomalo-bangla%2F2025-08-07%2Fdjnn070d%2FIMAGE-1075547.png?rect=0%2C32%2C1800%2C945&w=1200&ar=40%3A21&auto=format%2Ccompress&ogImage=true&mode=crop&overlay=https%3A%2F%2Fmedia.prothomalo.com%2Fprothomalo-bangla%2F2024-09-22%2F5lwyn5je%2Fdefaultog.jpg&overlay_position=bottom&overlay_width_pct=1",
            "body": "<html><body><div><div class=\"story-element story-element-text\"><div><p>ভিসা জানিয়েছে, দেশের ব্যাংক, মোবাইলে আর্থিক সেবাদাতা প্রতিষ্ঠান (এমএফএস), ফিনটেক, সরকারি সংস্থা, আন্তর্জাতিক উন্নয়ন সংস্থা, কৃষি প্রযুক্তিভিত্তিক প্রতিষ্ঠান, কূটনৈতিক মিশন, এভিয়েশন ই-কমার্স, রিটেইলসহ ৬০টির বেশি প্রতিষ্ঠানের প্রতিনিধিরা অনুষ্ঠানে উপস্থিত ছিলেন। অনুষ্ঠানে প্রধান অতিথি ছিলেন গভর্নর আহসান এইচ মনসুর। স্বাগত বক্তব্য দেন ভিসার বাংলাদেশ, নেপাল ও ভুটানের কান্ট্রি ম্যানেজার সাব্বির আহমেদ এবং ভারত ও দক্ষিণ এশিয়ার হেড অব প্রোডাক্ট রামাকৃষ্ণান গোপালান। আরও বক্তব্য দেন ভিসার ভারত ও দক্ষিণ এশিয়ার গ্রুপ কান্ট্রি ম্যানেজার সন্দ্বীপ ঘোষ। </p></div></div></div></body></html>"
        },
        {
            "title": "৫ আগস্টের বিজয় কোনো একক দলের পক্ষে সম্ভব ছিল না: তারেক রহমান | প্রথম আলো",
            "time": "2025-08-07T06:51:40",
            "imgUrl": "https://media.prothomalo.com/prothomalo-bangla%2F2025-08-07%2F5q10ww40%2FTarique-Rahman.png?rect=0%2C36%2C1920%2C1008&w=1200&ar=40%3A21&auto=format%2Ccompress&ogImage=true&mode=crop&overlay=https%3A%2F%2Fmedia.prothomalo.com%2Fprothomalo-bangla%2F2022-01%2F5a36c819-05a2-4bfb-ac50-57dd67355acb%2FBanner_7814X143.jpg&overlay_position=bottom&overlay_width_pct=1",
            "body": "<html><body><div><div class=\"story-title-info rG-CW\"><p><h1 data-title-0=\"৫ আগস্টের বিজয় কোনো একক দলের পক্ষে সম্ভব ছিল না: তারেক রহমান\" class=\"nA4h1 \">৫ আগস্টের বিজয় কোনো একক দলের পক্ষে সম্ভব ছিল না: তারেক রহমান</h1></p><div class=\"N8GaX\"><div class=\"XjL8O\"><div class=\"story-metadata-wrapper H6cQ5\"><p class=\"author-read-time-wrapper D-0u1\"></p><div class=\"time-social-share-wrapper _24WTx\"><div class=\"xuoYp\"><time datetime=\"2025-08-07T13:03:53+06:00\"><span>আপডেট: ০৭ আগস্ট ২০২৫, ০৭: ০৩ </span></time><svg xmlns=\"http://www.w3.org/2000/svg\" id=\"up-down\" viewbox=\"0 0 7.187 10\"><path id=\"Path_269\" d=\"M17.539 62.754h5.978a.6.6 0 0 1 .427 1.03l-2.989 2.989a.6.6 0 0 1-.852 0l-2.992-2.989a.6.6 0 0 1 .428-1.03zm6.405-2.638l-2.989-2.989a.6.6 0 0 0-.852 0l-2.992 2.989a.6.6 0 0 0 .427 1.03h5.978a.6.6 0 0 0 .428-1.03z\" data-name=\"Path 269\" transform=\"translate(-16.934 -56.95)\" fill=\"#00000061\"></path></svg></div></div></div></div></div></div></div></body></html>"
        },
        {
            "title": "মাত্র ১০ বছর বয়সে বাবার সঙ্গে শেষ দেখা হয় ওবামার। | প্রথম আলো",
            "time": "2025-08-07T06:48:00",
            "imgUrl": "https://media.prothomalo.com/prothomalo-bangla%2F2025-08-07%2Fttpuw0ib%2FBarack_Obama_4.webp?w=1200&ar=40%3A21&auto=format%2Ccompress&ogImage=true&mode=crop&overlay=https%3A%2F%2Fmedia.prothomalo.com%2Fprothomalo-bangla%2F2024-09-22%2F5lwyn5je%2Fdefaultog.jpg&overlay_position=bottom&overlay_width_pct=1",
            "body": "<html><body><div><div class=\"story-element story-element-text\"><div><p>ওবামার মা স্ট্যানলি অ্যান ডানহাম ছিলেন ইউরোপীয় বংশোদ্ভূত একজন শ্বেতাঙ্গ মার্কিন। ডানহাম পরিবার বিভিন্ন সময়ে যুক্তরাষ্ট্রের কানসাস, টেক্সাস ও ওয়াশিংটন অঙ্গরাজ্যে বসবাস করেছে। পর তারা হাওয়াইয়ের হনলুলুতে বসবাস শুরু করে। ১৯৬০ সালে হাওয়াই বিশ্ববিদ্যালয়ে রুশ ভাষা শেখার একটি ক্লাসে অ্যান ডানহামের দেখা হয় বারাক ওবামা সিনিয়রের সঙ্গে। কিশোর বয়স পর্যন্ত কেনিয়ার একটি গ্রামে বড় হওয়া ওবামা সিনিয়র বৃত্তি নিয়ে যুক্তরাষ্ট্রে পড়তে গিয়েছিলেন।</p><p>দেখা থেকে আলাপ-পরিচয়, পরিচয়ের এক বছরের মাথায় তাঁরা বিয়ে করেন। বিয়ের বছরই জন্ম হয় ওবামার। ছোট্ট ওবামার বয়স যখন মাত্র দুই বছর, তখন বারাক সিনিয়র হার্ভার্ড বিশ্ববিদ্যালয়ে পড়াশোনার জন্য যুক্তরাষ্ট্রের মূল ভূখণ্ডে চলে যান।</p><p>তার কিছুদিন পর ১৯৬৪ সালে অ্যান ও বারাক সিনিয়রের বিচ্ছেদ ঘটে। বাবা-মায়ের বিচ্ছেদের পর ওবামা তাঁর বাবাকে জীবনে আর মাত্র একবার দেখেছিলেন। ১৯৭১ সালে ওবামা সিনিয়র খুব সংক্ষিপ্ত সফরে যখন হাওয়াই এসেছিলেন, তখন শেষবার বাবা-ছেলের দেখা হয়। সে সময় ওবামার বয়স ছিল মাত্র ১০ বছর।</p><p>পরে অ্যান দ্বিতীয়বার বিয়ে করেন। এবারও এক বিদেশি ছাত্র, ইন্দোনেশিয়ার লোলো সোয়েতোরোকে। মায়ের সঙ্গে ইন্দোনেশিয়ার জাকার্তা চলে যান ওবামা। সেখানে সৎবাবা, মা ও সৎবোন মায়ার সঙ্গে কয়েক বছর বসবাস করেন ওবামা। ইন্দোনেশিয়ায় একটি সরকারি স্কুলে পড়ার সময় ইসলাম ধর্মের শিক্ষা নেন, পাশাপাশি একটি ক্যাথলিক বেসরকারি স্কুলেও ভর্তি ছিলেন, যেখানে তিনি খ্রিষ্টধর্মের শিক্ষা পেয়েছেন।</p><p>ওবামার মা ছিলেন একজন নৃবিজ্ঞানী। ছেলের লেখাপড়া নিয়ে উদ্বেগ থেকে তিনি ওবামাকে যুক্তরাষ্ট্রে নানা-নানির কাছে পাঠিয়ে দেন। ওবামা স্কুলে পড়ার সময়ই তাঁর মা দ্বিতীয়বার বিবাহবিচ্ছেদ করে হাওয়াই ফিরে যান। সেখানে লেখাপড়া শেষে অ্যান আবারও কাজের জন্য ইন্দোনেশিয়ায় চলে যান।</p></div></div></div></body></html>"
        },
        {
            "title": "পররাষ্ট্র মন্ত্রণালয়ের আঞ্চলিক দপ্তর চালু হচ্ছে চট্টগ্রামে | প্রথম আলো",
            "time": "2025-08-07T06:45:56",
            "imgUrl": "https://media.prothomalo.com/prothomalo-bangla%2F2024-01%2F61d4cece-1ddc-43d2-b445-1d379f1a2035%2Fprothomalo_import_media_2019_08_21_2e14902cb4d0c3eb0cdc6536bc290cdf_5d5cecf8db933.webp?rect=0%2C0%2C640%2C336&w=1200&ar=40%3A21&auto=format%2Ccompress&ogImage=true&mode=crop&overlay=https%3A%2F%2Fmedia.prothomalo.com%2Fprothomalo-bangla%2F2024-08-31%2F1m4oa2xi%2FBanner_7814X143.jpg&overlay_position=bottom&overlay_width_pct=1",
            "body": "<html><body><div><div class=\"story-element story-element-text\"><div><p>সচিব জানান, পররাষ্ট্র মন্ত্রণালয়ের দপ্তর চালু হলে শুধু কনস্যুলার সেবা নয়, চট্টগ্রামে সহকারী ভারতীয় হাইকমিশনারের অফিসের সঙ্গে কূটনৈতিক কার্যক্রম সমন্বয়ের কাজও করা যাবে। পাশাপাশি দপ্তরটি আঞ্চলিক পর্যায়ে বিভিন্ন আন্তর্জাতিক সফর, প্রতিনিধিদলের সমন্বয় ও প্রয়োজনীয় কূটনৈতিক কার্যক্রম পরিচালনা করবে।</p><p>পররাষ্ট্র মন্ত্রণালয়ের কর্মকর্তারা জানান, চট্টগ্রামে মন্ত্রণালয়ের দপ্তর চালু হলে বৃহত্তর চট্টগ্রাম বিভাগের লোকজন সরাসরি কনস্যুলার সেবা পাবেন। বর্তমানে নথিপত্র সত্যায়নের জন্য তাঁদের ঢাকায় যেতে হয়। নতুন এই আঞ্চলিক অফিস চালু হলে চট্টগ্রাম, কক্সবাজার, বান্দরবান, রাঙামাটি, খাগড়াছড়ি, ফেনী ও নোয়াখালী অঞ্চলের জনগণ স্থানীয়ভাবে এসব সেবা পাবেন। এতে সময় বাঁচবে, সেবার মানও উন্নত হবে।</p></div></div></div></body></html>"
        },
        {
            "title": "আব্বাস নিজে না খেয়ে মাস্তানকে খাওয়াতেন, বানিয়েছেন শাহরুখের সিনেমা | প্রথম আলো",
            "time": "2025-08-07T06:45:21",
            "imgUrl": "https://media.prothomalo.com/prothomalo-bangla%2F2025-07-24%2Fssc9nu7b%2Fdf0cce65-59cb-4e04-9368-b884afa07406.jpg?rect=0%2C0%2C1600%2C840&w=1200&ar=40%3A21&auto=format%2Ccompress&ogImage=true&mode=crop&overlay=https%3A%2F%2Fmedia.prothomalo.com%2Fprothomalo-bangla%2F2025-08-04%2Fftdzysgr%2FStarts-from-250-Entertainment.jpg&overlay_position=bottom&overlay_width_pct=1",
            "body": "<html><body><div><div class=\"story-element story-element-text\"><div><p>আব্বাস-মাস্তান তাঁদের ক্যারিয়ারে উপহার দিয়েছেন ‘বাজিগর’, ‘খিলাড়ি’, ‘সোলজার’, ‘টারজান: দ্য ওয়ান্ডার কার’, ‘রেস’, ‘রেস ২’-এর মতো সুপারহিট সব সিনেমা। তাঁদের গল্প রূপকথার মতোই—যেখানে আত্মত্যাগ, লড়াই, আর পারিবারিক বন্ধন একাকার হয়ে তৈরি করেছে বলিউডের ইতিহাসের এক অসাধারণ অধ্যায়।</p><p>তথ্যসূত্র: ইন্ডিয়ান এক্সপ্রেস</p></div></div></div></body></html>"
        },
        {
            "title": "কাঁটাবনে ট্রাক ও পিকআপের মুখোমুখি সংঘর্ষে নিহত ১ | প্রথম আলো",
            "time": "2025-08-07T06:41:24",
            "imgUrl": "https://media.prothomalo.com/prothomalo-bangla%2F2023-11%2Fbd4fc6c6-7409-4c71-92f8-1a7f024062a7%2Froad_accident_01.png?rect=0%2C0%2C1600%2C840&w=1200&ar=40%3A21&auto=format%2Ccompress&ogImage=true&mode=crop&overlay=https%3A%2F%2Fmedia.prothomalo.com%2Fprothomalo-bangla%2F2024-08-31%2F1m4oa2xi%2FBanner_7814X143.jpg&overlay_position=bottom&overlay_width_pct=1",
            "body": "<html><body><div><div class=\"story-element story-element-text\"><div><p>দুর্ঘটনায় আহত হয়েছেন পিকআপচালক মাসুদ রানা (৪২) ও তাঁর ছেলে সালমান (১৬)। দুজনকেই ঢাকা মেডিকেল কলেজ হাসপাতালে চিকিৎসা দেওয়া হচ্ছে।</p><p>রাজধানীর শাহবাগ থানার ভারপ্রাপ্ত কর্মকর্তা (ওসি) খালিদ মনসুর প্রথম আলোকে বলেন, দুর্ঘটনার পর ট্রাক নিয়ে চালক পালিয়ে গেছেন।</p><p>ঢাকা মেডিকেল কলেজ হাসপাতালে চিকিৎসাধীন সালমান জানান, গাজীপুরের পুবাইল থেকে ভাঙারি মালামাল নিয়ে তাঁরা তিনজন ঢাকায় এসেছিলেন। মালামাল নামিয়ে ফেরার পথে কাঁটাবন মোড়ে দ্রুতগতির একটি ট্রাকের সঙ্গে তাঁদের পিকআপের মুখোমুখি সংঘর্ষ হয়। এতে তাঁরা তিনজন আহত হন, পরে একরামের মৃত্যু হয়।</p></div></div></div></body></html>"
        },
        {
            "title": "‘বন্ধু’ ট্রাম্পের শুল্কের ঠ্যালা সামলাতে পারবে তো মোদির ভারত! | প্রথম আলো",
            "time": "2025-08-07T06:40:18",
            "imgUrl": "https://media.prothomalo.com/prothomalo-bangla%2F2025-08-07%2Fwb9veyee%2F931137-01-02.jpg?rect=0%2C218%2C4741%2C2489&w=1200&ar=40%3A21&auto=format%2Ccompress&ogImage=true&mode=crop&overlay=https%3A%2F%2Fmedia.prothomalo.com%2Fprothomalo-bangla%2F2024-09-22%2F5lwyn5je%2Fdefaultog.jpg&overlay_position=bottom&overlay_width_pct=1",
            "body": "<html><body><div><div class=\"story-element story-element-text\"><div><p>এই সিদ্ধান্তে অনেক বিশেষজ্ঞই বিস্মিত হয়েছেন। কারণ ভারতই প্রথম কয়েকটি দেশের মধ্যে ছিল যারা যুক্তরাষ্ট্রের সঙ্গে বাণিজ্য আলোচনায় বসেছিল। এমনকি ট্রাম্প ও ভারতের প্রধানমন্ত্রী নরেন্দ্র মোদি একে অপরের প্রতি বারবার প্রকাশ্যে প্রশংসা করেছেন। নিজেদের ‘বন্ধু’ বলেও অভিহিত করেছেন।</p><p>এই মুহূর্তে ব্রাজিল ছাড়া আর কোনো দেশ এত বেশি শুল্কের মুখে পড়েনি। এশিয়া প্যাসিফিক ফাউন্ডেশন অব কানাডার কৌশল ও গবেষণা বিভাগের ভাইস প্রেসিডেন্ট ভিনা নাজিবুল্লাহ বলেছেন, ‘বাণিজ্য আলোচনা ভেঙে যাওয়া ছিল সত্যি অপ্রত্যাশিত।’</p><p>তিনি আরও বলেন, ‘এটি দুই দেশের সম্পর্কের জন্য অত্যন্ত কঠিন সময়। এটি সম্ভবত বহু বছরের মধ্যে সবচেয়ে খারাপ মুহূর্ত। এখন ভারত এমন একটি ক্ষুদ্র গোষ্ঠীতে পড়ে গেছে যারা কোনো চুক্তি ছাড়াই সবচেয়ে বেশি শুল্কের মুখোমুখি হয়েছে। এখন দরকার বাস্তবভিত্তিক কিছু পদক্ষেপ, যাতে আবারও পারস্পরিক আস্থা গড়ে তোলা যায়।’</p><p>যদিও এই ৫০ শতাংশ শুল্ক আগামী তিন সপ্তাহ পর থেকে কার্যকর হবে এবং তা হঠাৎ করেই এসেছে বলে মনে হচ্ছে, তবে গত কয়েক সপ্তাহে ঘটে যাওয়া বেশ কিছু ঘটনা থেকে দুই দেশের মতবিরোধের ইঙ্গিত পাওয়া যাচ্ছিল।</p><p>গত সপ্তাহেই ট্রাম্প হুমকি দেন, রাশিয়ার কাছ থেকে তেল ও অস্ত্র কেনার জন্য তিনি ভারতকে শাস্তি দেবেন। বাণিজ্য আলোচনা অচলাবস্থায় পড়ায় ক্ষোভ প্রকাশ করে তিনি যুক্তরাষ্ট্র ও ভারত—দুই দেশকেই ‘মৃত অর্থনীতি’ বলে উল্লেখ করেন।</p></div></div></div></body></html>"
        },
        {
            "title": "‘তাড়াতাড়ি ঘুম ভাঙছিল, না হলে সব জিনিসপত্র নষ্ট হয়ে যেত পানিতে’ | প্রথম আলো",
            "time": "2025-08-07T06:31:00",
            "imgUrl": "https://media.prothomalo.com/prothomalo-bangla%2F2025-08-07%2F1ccvrjbj%2Fchittagong.jpg?rect=0%2C0%2C1280%2C672&w=1200&ar=40%3A21&auto=format%2Ccompress&ogImage=true&mode=crop&overlay=https%3A%2F%2Fmedia.prothomalo.com%2Fprothomalo-bangla%2F2024-08-31%2F1m4oa2xi%2FBanner_7814X143.jpg&overlay_position=bottom&overlay_width_pct=1",
            "body": "<html><body><div><div class=\"story-element story-element-text\"><div><p>আজ ভোররাতের ভারী বৃষ্টিতে নগরের বহদ্দারহাট, মুরাদপুর, চকবাজার, শুলকবহর, কাতালগঞ্জ, কাপাসগোলা, বাদুড়তলা, জিইসি মোড়, প্রবর্তক মোড়, ঝাউতলা, জাকির হোসেন সড়কের রেলক্রসিং, চান্দগাঁও আবাসিক এলাকা, চান্দগাঁওয়ের ফরিদারপাড়া, নয়াবাজার, মৌসুমি আবাসিক এলাকা, আগ্রাবাদ বাণিজ্যিক এলাকাসহ অনেক এলাকায় গোড়ালি থেকে হাঁটুসমান পানি জমে ছিল।</p><p>নগরের ঝাউতলা এলাকার বাসিন্দা শহীদুল ইসলাম বলেন, সকালের বৃষ্টিতে তাঁদের এলাকায় হাঁটুসমান পানি উঠেছিল। পানি জমে ছিল দেড় থেকে দুই ঘণ্টা। অফিসে যেতে শুধু একটা জায়গায় না, অন্তত চারটি জায়গায় পানি জমে থাকতে দেখেন। কিছু দূর পরপর পানি জমে থাকায় অফিসে যেতেও দেরি হয়।</p></div></div></div></body></html>"
        },
        {
            "title": "ডিবি কার্যালয়ে তাঁর সঙ্গে ফুটবলের মতো আচরণ করা হতো, বললেন নুরুল হক | প্রথম আলো",
            "time": "2025-08-07T06:30:00",
            "imgUrl": "https://media.prothomalo.com/prothomalo-bangla%2F2025-08-06%2Fpvzf2yfp%2FVid20250806172717.00002501.Still006.jpg?rect=0%2C0%2C1920%2C1008&w=1200&ar=40%3A21&auto=format%2Ccompress&ogImage=true&mode=crop&overlay=https%3A%2F%2Fmedia.prothomalo.com%2Fprothomalo-bangla%2F2022-01%2F5a36c819-05a2-4bfb-ac50-57dd67355acb%2FBanner_7814X143.jpg&overlay_position=bottom&overlay_width_pct=1",
            "body": "<html><body><div><div class=\"story-title-info rG-CW\"><p><h1 data-title-0=\"ডিবি কার্যালয়ে তাঁর সঙ্গে ফুটবলের মতো আচরণ করা হতো, বললেন নুরুল হক\" class=\"nA4h1 \">ডিবি কার্যালয়ে তাঁর সঙ্গে ফুটবলের মতো আচরণ করা হতো, বললেন নুরুল হক</h1></p><div class=\"N8GaX\"><div class=\"XjL8O\"><div class=\"story-metadata-wrapper H6cQ5\"><p class=\"author-read-time-wrapper D-0u1\"></p><div class=\"time-social-share-wrapper _24WTx\"><p class=\"xuoYp\"><time datetime=\"2025-08-07T12:30:00+06:00\"><span>প্রকাশ: ০৭ আগস্ট ২০২৫, ০৬: ৩০ </span></time></p></div></div></div></div></div></div></body></html>"
        },
        {
            "title": "দুই স্তরের টেস্ট: ইংল্যান্ড সতর্ক ও উদ্বিগ্ন, লাভ হলে আপত্তি নেই অস্ট্রেলিয়ার | প্রথম আলো",
            "time": "2025-08-07T06:25:20",
            "imgUrl": "https://media.prothomalo.com/prothomalo-bangla%2F2025-08-07%2Fctrqpk60%2FLogo.jpg?rect=0%2C0%2C877%2C460&w=1200&ar=40%3A21&auto=format%2Ccompress&ogImage=true&mode=crop&overlay=https%3A%2F%2Fmedia.prothomalo.com%2Fprothomalo-bangla%2F2025-08-04%2F599lv4ex%2FCashout-free-Sports-Lifestyle.png&overlay_position=bottom&overlay_width_pct=1",
            "body": "<html><body><div><div class=\"story-element story-element-text\"><div><p>সম্প্রতি ওভালে ইংল্যান্ড–ভারতের সিরিজ নির্ধারণী টেস্ট চলাকালীন ইসিবি চেয়ারম্যান রিচার্ড থম্পসন <em>বিবিসিকে</em> বলেন, ‘আমরা যদি খারাপ সময় পার করি এবং দ্বিতীয় স্তরে নেমে যাই, তাহলে কি অস্ট্রেলিয়া বা ভারতের বিপক্ষে খেলব না? এটা হতে পারে না। এখানে যুক্তির প্রয়োগ জরুরি।’</p><p>থম্পসন মনে করেন, বর্তমানে বিশ্বব্যাপী টি–টোয়েন্টি লিগের ভিড়ে দ্বিপক্ষীয় টেস্ট সিরিজের গুরুত্ব অনেকটাই কমে গেছে। তাঁর বিশ্বাস, বিশ্ব টেস্ট চ্যাম্পিয়নশিপের কাঠামোতেই কিছু পরিবর্তন আনলে দুই স্তরবিশিষ্ট টেস্টের প্রয়োজন পড়বে না।</p></div></div></div></body></html>"
        },
        {
            "title": "মাসে কতবার ইমারজেন্সি পিল খাওয়া নিরাপদ | প্রথম আলো",
            "time": "2025-08-07T06:14:44",
            "imgUrl": "https://media.prothomalo.com/prothomalo-bangla%2F2023-02%2F726095ac-9474-46a3-a8b3-2828b262d94b%2Fadce3d3ebc8c209a2213e75ac1be2d14.jpg?rect=0%2C98%2C1242%2C652&w=1200&ar=40%3A21&auto=format%2Ccompress&ogImage=true&mode=crop&overlay=https%3A%2F%2Fmedia.prothomalo.com%2Fprothomalo-bangla%2F2025-08-04%2F599lv4ex%2FCashout-free-Sports-Lifestyle.png&overlay_position=bottom&overlay_width_pct=1",
            "body": "<html><body><div><div class=\"story-element story-element-text\"><div><p>যত বেশি ইমারজেন্সি পিল সেবন করা হবে, পার্শ্বপ্রতিক্রিয়ার ঝুঁকি তত বাড়বে। তাই কেবল জরুরি পরিস্থিতিতে তা সেবনের পরামর্শ দেওয়া হয়। ইমারজেন্সি পিলের একটি ধরনে থাকে লেভোনরজেস্ট্রেল। অন্যটিতে থাকে ইউলিপ্রিস্টাল অ্যাসিটেট। যেকোনো একটি বেছে নেওয়া যেতে পারে।</p><p>লেভোনরজেস্ট্রেল মাসে দুইবারের বেশি ব্যবহার করা উচিত নয়। আর ইউলিপ্রিস্টাল অ্যাসিটেট মাসে একবারের বেশি ব্যবহার করা ঠিক নয়। যাঁর সপ্তাহে দুইবারের বেশি ইমারজেন্সি পিল সেবনের প্রয়োজন দেখা দেয়, তাঁর অবশ্যই এর পরিবর্তে একটি নিয়মিত জন্মনিয়ন্ত্রণপদ্ধতি বেছে নেওয়া উচিত।</p></div></div></div></body></html>"
        },
        {
            "title": "ভরসা যখন ঘোড়ার গাড়ি | প্রথম আলো",
            "time": "2025-08-07T06:12:49",
            "imgUrl": "https://media.prothomalo.com/prothomalo-bangla%2F2025-08-07%2Fxfds6blh%2F07082025-cm-16.jpg?rect=0%2C19%2C1164%2C611&w=1200&ar=40%3A21&auto=format%2Ccompress&ogImage=true&mode=crop&overlay=https%3A%2F%2Fmedia.prothomalo.com%2Fprothomalo-bangla%2F2024-08-31%2F1m4oa2xi%2FBanner_7814X143.jpg&overlay_position=bottom&overlay_width_pct=1",
            "body": "<html><body><div><div class=\"story-element story-element-text\"><div><p>চরপেঁচাকোলায় প্রায় দেড় শ পরিবারের বসবাস। প্রায় প্রতিটি বাড়িতে রয়েছে ঘোড়ার গাড়ি। নিয়মিত ঘোড়ার পরিচর্যাও করতে হয় তাদের। চরবাসীর সঙ্গে আলাপচারিতায় জানা যায়, প্রতিদিন একেকটি ঘোড়ার জন্য ৩০০ থেকে ৫০০ টাকার খাবার লাগে। এর মধ্যে রয়েছে খইল, ভুসি, ঘাস, ছোলা, ধানের কুঁড়া ও চাল। কখনো কখনো থাকে খড়। এ ছাড়া চিকিৎসা খরচ তো আছেই।</p><p>অনেকেই নিজেদের প্রয়োজন মিটিয়ে ঘোড়ার গাড়ি ভাড়াতেও চালান। এভাবে দিনে ৫০০ থেকে ২ হাজার টাকা পর্যন্ত আয় হয়। কথা হচ্ছিল চরপেঁচাকোলার চালক কামরুল ইসলামের সঙ্গে। তিনি বলেন, ‘জমির ফসল আর বাড়ির লোকজনের যাতায়াতের জন্য প্রায় সারা দিন গাড়ি লাগে। কখনো কাজ না থাকলে ভাড়ার বিনিময়ে অন্যের জন্য গাড়ি চালাই। তখন বাজারে মালপত্র বা মানুষ পৌঁছে দিই।’</p><p>চরবাসীর দেওয়া তথ্য অনুসারে, একেকটি ঘোড়ার গাড়ি তৈরিতে এখন খরচ পড়ে ২০–৩০ হাজার টাকা। গাড়ির কাঠ ও লোহার অংশ আলাদাভাবে তৈরি করা হয়। স্থানীয় মিস্ত্রিরা পাঁচ থেকে ছয় দিনের মধ্যে একটি গাড়ি তৈরি করতে পারেন। গাড়ির জন্য সাধারণ মানের একেকটি ঘোড়া কিনতে লাগে ৪০–৬০ হাজার টাকা। তবে ভালো মানের ঘোড়া হলে গুনতে হয় লাখ টাকার বেশি।</p></div></div></div></body></html>"
        },
        {
            "title": "ডিএমপির সাবেক কমিশনার হাবিবুরসহ ৫ আসামির বিরুদ্ধে আনুষ্ঠানিক অভিযোগ দাখিল | প্রথম আলো",
            "time": "2025-08-07T06:11:52",
            "imgUrl": "https://media.prothomalo.com/prothomalo-bangla%2F2025-08-07%2F2tua3ilg%2FHabibur-Rahman.png?rect=0%2C29%2C932%2C489&w=1200&ar=40%3A21&auto=format%2Ccompress&ogImage=true&mode=crop&overlay=https%3A%2F%2Fmedia.prothomalo.com%2Fprothomalo-bangla%2F2024-08-31%2F1m4oa2xi%2FBanner_7814X143.jpg&overlay_position=bottom&overlay_width_pct=1",
            "body": "<html><body><div><div class=\"story-element story-element-text\"><div><p>বাকি চার আসামি হলেন ডিএমপির খিলগাঁও অঞ্চলের সাবেক অতিরিক্ত উপকমিশনার (এডিসি) মো. রাশেদুল ইসলাম, রামপুরা থানার সাবেক ভারপ্রাপ্ত কর্মকর্তা (ওসি) মো. মশিউর রহমান, রামপুরা থানার সাবেক উপপরিদর্শক (এসআই) তারিকুল ইসলাম ভূঁইয়া ও রামপুরা পুলিশ ফাঁড়ির সাবেক সহকারী উপপরিদর্শক (এএসআই) চঞ্চল চন্দ্র সরকার।</p><p>পাঁচ আসামির মধ্যে শুধু চঞ্চল গ্রেপ্তার আছেন। বাকি চার আসামি পলাতক।</p></div></div></div></body></html>"
        },
        {
            "title": "মেট্রোরেলের দুই স্টেশনে ঢাকা ব্যাংকের সিআরএম বুথ চালু | প্রথম আলো",
            "time": "2025-08-07T06:10:00",
            "imgUrl": "https://media.prothomalo.com/prothomalo-bangla%2F2025-08-07%2Fj0el8ybv%2F06-08-25-DHAKA-BANK-METRO-STATION060214.png?rect=0%2C0%2C1800%2C945&w=1200&ar=40%3A21&auto=format%2Ccompress&ogImage=true&mode=crop&overlay=https%3A%2F%2Fmedia.prothomalo.com%2Fprothomalo-bangla%2F2024-09-22%2F5lwyn5je%2Fdefaultog.jpg&overlay_position=bottom&overlay_width_pct=1",
            "body": "<html><body><div><div class=\"story-element story-element-text\"><div><p>এক সংবাদ বিজ্ঞপ্তিতে ঢাকা ব্যাংক এ তথ্য জানিয়েছে। এতে বলা হয়, সম্প্রতি এমআরটি লাইন-৬-এর ফার্মগেট স্টেশনে নতুন বুথ উদ্বোধন করা হয়। উদ্বোধনী অনুষ্ঠানে উপস্থিত ছিলেন ঢাকা ব্যাংকের ব্যবস্থাপনা পরিচালক (এমডি) শেখ মোহাম্মদ মারুফ, ডিএমডি মো. মোস্তাক আহমেদ, রিটেইল বিজনেস বিভাগের প্রধান এইচ এম মোস্তাফিজুর রহমান, সাধারণ সেবা বিভাগের প্রধান মো. আলতামাস নির্জর, কারওয়ান বাজার শাখার ব্যবস্থাপক সৈয়দ আশরাফুল আমিন প্রমুখ। এ ছাড়া ঢাকা ম্যাস ট্রানজিট কোম্পানি লিমিটেডের (ডিএমটিসিএল) এমডি ফারুক আহমেদ, ডিএমটিসিএলের প্রকল্প পরিচালক মো. জাকারিয়া, পরিচালক (প্রশাসন) এ কে এম খায়রুল আলম ও কোম্পানি সচিব খোন্দকার এহতেশামুল কবীর অনুষ্ঠানে উপস্থিত ছিলেন। </p></div></div></div></body></html>"
        },
        {
            "title": "জয়া আহসান: ভূগোল মেনে আর্টিস্ট হয় না | প্রথম আলো",
            "time": "2025-08-07T06:00:00",
            "imgUrl": "https://media.prothomalo.com/prothomalo-bangla%2F2025-08-06%2Fw4la9kdt%2Fjayaweb.jpg?rect=0%2C0%2C1920%2C1008&w=1200&ar=40%3A21&auto=format%2Ccompress&ogImage=true&mode=crop&overlay=https%3A%2F%2Fmedia.prothomalo.com%2Fprothomalo-bangla%2F2022-01%2F5a36c819-05a2-4bfb-ac50-57dd67355acb%2FBanner_7814X143.jpg&overlay_position=bottom&overlay_width_pct=1",
            "body": "<html><body><div><div class=\"story-title-info rG-CW\"><p><h1 data-title-0=\"জয়া আহসান: ভূগোল মেনে আর্টিস্ট হয় না\" class=\"nA4h1 \">জয়া আহসান: ভূগোল মেনে আর্টিস্ট হয় না</h1></p><div class=\"N8GaX\"><div class=\"XjL8O\"><div class=\"story-metadata-wrapper H6cQ5\"><p class=\"author-read-time-wrapper D-0u1\"></p><div class=\"time-social-share-wrapper _24WTx\"><p class=\"xuoYp\"><time datetime=\"2025-08-07T12:00:00+06:00\"><span>প্রকাশ: ০৭ আগস্ট ২০২৫, ০৬: ০০ </span></time></p></div></div></div></div></div></div></body></html>"
        }
    ]
}