{
    "source": "প্রথম আলো",
    "articles": [
        {
            "title": "থাইল্যান্ডে নির্বাচন ও গণভোটের ফলাফল কী? | প্রথম আলো",
            "time": "2026-02-09T17:48:56",
            "imgUrl": "https://media.prothomalo.com/prothomalo-bangla%2F2026-02-09%2Fi2b2ddod%2FWEB.jpg?rect=0%2C109%2C800%2C420&w=1200&ar=40%3A21&auto=format%2Ccompress&ogImage=true&mode=crop&overlay=https%3A%2F%2Fmedia.prothomalo.com%2Fprothomalo-bangla%2F2022-01%2F5a36c819-05a2-4bfb-ac50-57dd67355acb%2FBanner_7814X143.jpg&overlay_position=bottom&overlay_width_pct=1",
            "body": "<html><body><div><div class=\"story-title-info rG-CW\"><p><h1 data-title-0=\"থাইল্যান্ডে নির্বাচন ও গণভোটের ফলাফল কী? \" class=\"nA4h1 \">থাইল্যান্ডে নির্বাচন ও গণভোটের ফলাফল কী? </h1></p><div class=\"N8GaX\"><div class=\"XjL8O\"><div class=\"story-metadata-wrapper H6cQ5\"><p class=\"author-read-time-wrapper D-0u1\"></p><div class=\"time-social-share-wrapper _24WTx\"><p class=\"xuoYp\"><time datetime=\"2026-02-09T23:48:56+06:00\"><span>প্রকাশ: ০৯ ফেব্রুয়ারি ২০২৬, ১৭: ৪৮ </span></time></p></div></div></div></div></div></div></body></html>"
        },
        {
            "title": "বিকাশ নম্বর বা আইডি নম্বর চাইলে সতর্ক থাকবেন: তারেক রহমান | প্রথম আলো",
            "time": "2026-02-09T17:46:47",
            "imgUrl": "https://media.prothomalo.com/prothomalo-bangla%2F2026-02-09%2F5fvn3nov%2FTarique-jurain.jpg?rect=0%2C0%2C1280%2C672&w=1200&ar=40%3A21&auto=format%2Ccompress&ogImage=true&mode=crop&overlay=https%3A%2F%2Fmedia.prothomalo.com%2Fprothomalo-bangla%2F2022-01%2F5a36c819-05a2-4bfb-ac50-57dd67355acb%2FBanner_7814X143.jpg&overlay_position=bottom&overlay_width_pct=1",
            "body": "<html><body><div><div class=\"story-element story-element-text\"><div><p>বিএনপির চেয়ারম্যান তারেক রহমান বলেছেন, ‘একটি দলের সদস্যরা আমাদের মা–বোনদের বিভ্রান্ত করছে। তাদের কাছে বিকাশ নম্বর চাইছে, আইডি (পরিচয়পত্র) নম্বর চাইছে…। এই সকল ব্যাপারে আমাদেরকে সতর্ক থাকতে হবে।’</p><p> আজ সোমবার সন্ধ্যায় রাজধানীর জুরাইনে ঢাকা-৪ আসনে ধানের শীষের প্রার্থী তানভীর আহমেদ রবিনের নির্বাচনী জনসভায় তারেক রহমান এ কথা বলেন।</p><p> তারেক রহমান বলেন, গত এক যুগের বেশি সময় ধরে শুধু জনগণের ভোটের অধিকারই নয়, তাদের গণতান্ত্রিক স্বাধীনতাও কেড়ে নেওয়া হয়েছে। তিনি বলেন, ‘আবারও গণতন্ত্রের বিপক্ষে ষড়যন্ত্র শুরু হয়েছে। এই ষড়যন্ত্র রুখে দিতে হবে।’</p><p> নেতা–কর্মীদের উদ্দেশে তারেক রহমান বলেন, ‘১২ তারিখের নির্বাচনে আপনাদের সতর্ক থাকতে হবে, চোখ-কান খোলা রাখতে হবে।’</p></div></div></div></body></html>"
        },
        {
            "title": "‘ভোট না, আমাগো এলাকায় উৎসব নিয়া আইছে দিপু’ | প্রথম আলো",
            "time": "2026-02-09T17:46:26",
            "imgUrl": "https://media.prothomalo.com/prothomalo-bangla%2F2026-02-09%2F62nz5z8o%2F%E0%A6%A8%E0%A6%BE%E0%A6%B0%E0%A6%BE%E0%A7%9F%E0%A7%A7.png?rect=0%2C0%2C3840%2C2016&w=1200&ar=40%3A21&auto=format%2Ccompress&ogImage=true&mode=crop&overlay=https%3A%2F%2Fmedia.prothomalo.com%2Fprothomalo-bangla%2F2024-08-31%2F1m4oa2xi%2FBanner_7814X143.jpg&overlay_position=bottom&overlay_width_pct=1",
            "body": "<html><body><div><div class=\"story-element story-element-text\"><div><p>সমাবেশের আগে মোস্তাফিজুর রহমান প্রথম আলোকে বলেন, রূপগঞ্জের অন্যতম প্রধান সংকট ভূমিদস্যুতা। যে যত বড় ক্ষমতাধরই হোক না কেন, জমি না কিনে কেউ যেন বালু ভরাট করতে না পারে, তা নিশ্চিত করা হবে। এ ছাড়া পূর্বাচলের প্লটগুলো যেন জমির মালিকেরা বুঝে পান, সে ব্যবস্থাও করা হবে।</p><p>‘মাদক’ চনপাড়াসহ রূপগঞ্জের অন্যতম বড় সমস্যা উল্লেখ করে মোস্তাফিজুর রহমান বলেন, ‘নারায়ণগঞ্জের ২০টি মাদকের স্পট তারেক রহমান চিহ্নিত করেছেন। তার মধ্যে কয়েকটি রূপগঞ্জে রয়েছে। আমরা দলগতভাবে মাদকের বিরুদ্ধে কাজ করব।’</p><p>স্থানীয় মানুষ যেন রূপগঞ্জের শিল্পকারখানায় কাজ পান, সে উদ্যোগ নেওয়া হবে বলেও জানান মোস্তাফিজুর রহমান। তিনি বলেন, ‘যদি কারখানামালিকেরা স্থানীয়দের কাজে নিতে ভয় পায়, তাহলে আমি নিজে আমার অঞ্চলের মানুষের জিম্মাদার হব।’</p><p>পানি ও শব্দদূষণ রোধে উদ্যোগী হওয়ার পাশাপাশি রূপগঞ্জে আবাসিক গ্যাস সংযোগ স্থাপনের উদ্যোগ নেওয়ার কথাও জানান এই বিএনপি নেতা। তিনি বলেন, ‘শিল্প ও আবাসনের কারণে রূপগঞ্জে প্রাকৃতিক জ্বালানি পাওয়া যাচ্ছে না। ফলে আমি তারেক রহমানের কাছে গ্যাস–সংকট সমাধানের আবেদন জানাব।’</p></div></div></div></body></html>"
        },
        {
            "title": "যুক্তরাষ্ট্রের সঙ্গে বাণিজ্যচুক্তি সই, পাল্টা শুল্ক কমল ১ শতাংশ | প্রথম আলো",
            "time": "2026-02-09T17:44:10",
            "imgUrl": "https://media.prothomalo.com/prothomalo-bangla%2F2026-02-03%2F6i59eqxw%2Fbangla.avif?rect=0%2C23%2C1200%2C630&w=1200&ar=40%3A21&auto=format%2Ccompress&ogImage=true&mode=crop&overlay=https%3A%2F%2Fmedia.prothomalo.com%2Fprothomalo-bangla%2F2025-11-23%2F1558a7oz%2Fdefaultog.webp&overlay_position=bottom&overlay_width_pct=1",
            "body": "<html><body><div><div class=\"story-element story-element-text\"><div><p>চুক্তি সই অনুষ্ঠান উপলক্ষে বাণিজ্য মন্ত্রণালয়ের ডব্লিউটিও অনুবিভাগের অতিরিক্ত সচিব খাদিজা নাজনীনের নেতৃত্বাধীন পাঁচ সদস্যের একটি দল ওয়াশিংটন গেছে। অন্য চারজনের মধ্যে রয়েছেন বাণিজ্য মন্ত্রণালয়ের দুই যুগ্ম সচিব ফিরোজ উদ্দিন আহমেদ ও মোস্তাফিজুর রহমান, সিনিয়র সহকারী সচিব শেখ শামসুল আরেফীন এবং জাতীয় রাজস্ব বোর্ডের (এনবিআর) কমিশনার রইছ উদ্দিন খান। পাঁচ সদস্যের প্রতিনিধিদলের সশরীর উপস্থিতিতে এই চুক্তি হয়।</p><p>চুক্তির বিষয়ে জানতে চাইলে বেসরকারি গবেষণা সংস্থা সেন্টার ফর পলিসি ডায়ালগের (সিপিডি) সম্মাননীয় ফেলো মোস্তাফিজুর রহমান প্রথম আলোকে বলেন, ‘চুক্তিতে কী কী শর্ত আছে, তা আমরা জানি না। আমি মনে করি, এই ধরনের চুক্তি বর্তমান অন্তর্বর্তী সরকারের শেষ সময়ে এসে করা মোটেই উচিত হয়নি। আমরা কিছু নতুন সুবিধা পেয়েছি, সেটিকে আমরা অর্জন হিসেবে মনে করতে পারি। কিন্তু তার বদলে কী কী শর্ত পূরণ করতে হবে বা বাংলাদেশকে কী কী করতে হবে, তা আমরা জানি না। ফলে এই চুক্তিতে বাংলাদেশ কতটা লাভবান হলো, তা এককথায় বলা মুশকিল। এই চুক্তির দায়ভার এসে পড়বে পরবর্তী সরকারের ওপর। সেই সরকার চুক্তি শর্তগুলো পূরণে কতটুকু প্রস্তুত এবং তাদের এসব বিষয়ে বর্তমানে সরকারের পক্ষ থেকে জানানো হয়েছে কি না, তা–ও বড় প্রশ্ন। তাই আমি মনে করি, চুক্তির লাভ–লোকসানের হিসাব কষতে হবে চুক্তিতে কী কী শর্ত আছে, তা সার্বিকভাবে পর্যালোচনার ভিত্তিতে।’</p></div></div></div></body></html>"
        },
        {
            "title": "নির্দেশনা নাকি অভিনয় - কোনটি পছন্দ? | প্রথম আলো",
            "time": "2026-02-09T17:39:45",
            "imgUrl": "https://media.prothomalo.com/prothomalo-bangla%2F2026-02-09%2Fjmbdjklb%2FTHUMBNAIL.jpg?rect=0%2C0%2C1920%2C1008&w=1200&ar=40%3A21&auto=format%2Ccompress&ogImage=true&mode=crop&overlay=https%3A%2F%2Fmedia.prothomalo.com%2Fprothomalo-bangla%2F2022-01%2F5a36c819-05a2-4bfb-ac50-57dd67355acb%2FBanner_7814X143.jpg&overlay_position=bottom&overlay_width_pct=1",
            "body": "<html><body><div><div class=\"story-title-info rG-CW\"><p class=\"print-entity-section-wrapper ut4Ac\"><h2 class=\"_-94Px\">মেরিল ক্যাফে লাইভ </h2></p><p><h1 data-title-0=\"নির্দেশনা নাকি অভিনয় - কোনটি পছন্দ?\" class=\"nA4h1 \">নির্দেশনা নাকি অভিনয় - কোনটি পছন্দ?</h1></p><div class=\"N8GaX\"><div class=\"XjL8O\"><div class=\"story-metadata-wrapper H6cQ5\"><p class=\"author-read-time-wrapper D-0u1\"></p><div class=\"time-social-share-wrapper _24WTx\"><p class=\"xuoYp\"><time datetime=\"2026-02-09T23:39:45+06:00\"><span>প্রকাশ: ০৯ ফেব্রুয়ারি ২০২৬, ১৭: ৩৯ </span></time></p></div></div></div></div></div></div></body></html>"
        },
        {
            "title": "অবশেষে সব পাঠ্যবই সরবরাহ করল এনসিটিবি | প্রথম আলো",
            "time": "2026-02-09T17:39:17",
            "imgUrl": "https://media.prothomalo.com/prothomalo-bangla%2F2026-02-09%2F6vxan4tp%2F%E0%A7%A8.avif?rect=0%2C44%2C622%2C327&w=1200&ar=40%3A21&auto=format%2Ccompress&ogImage=true&mode=crop&overlay=https%3A%2F%2Fmedia.prothomalo.com%2Fprothomalo-bangla%2F2024-08-31%2F1m4oa2xi%2FBanner_7814X143.jpg&overlay_position=bottom&overlay_width_pct=1",
            "body": "<html><body><div><div class=\"story-element story-element-text\"><div><p>শিক্ষাবর্ষ শুরুর এক মাস সাত দিনের মাথায় ৭ ফেব্রুয়ারি বিনা মূল্যের শতভাগ পাঠ্যপুস্তক সরবরাহ করা হয়েছে বলে জানিয়েছে জাতীয় শিক্ষাক্রম ও পাঠ্যপুস্তক বোর্ড (এনসিটিবি)। সোমবার এনসিটিবি এক সংবাদ বিজ্ঞপ্তি দিয়ে এ কথা জানিয়েছে।</p><p>এনসিটিবি জানিয়েছে, চলতি ২০২৬ শিক্ষাবর্ষে প্রাথমিক ও মাধ্যমিক স্তরে মোট ৩০ কোটি ২ লাখ ৫৫ হাজার ১৫৪টি পাঠ্যপুস্তক মুদ্রণ ও সরবরাহ করা হয়েছে। এর মধ্যে প্রাথমিক ও ইবতেদায়ি স্তরে ১১ কোটি ৭০ লাখ ৪৬ হাজার ৪৬১টি এবং মাধ্যমিক স্তরে ১৮ কোটি ৩২ লাখ ৮ হাজার ৬৯৩টি বই রয়েছে।</p></div></div></div></body></html>"
        },
        {
            "title": "বিশ্বকাপ না খেলায় শাস্তি হবে না বিসিবির, পাচ্ছে পুরস্কারও | প্রথম আলো",
            "time": "2026-02-09T17:39:16",
            "imgUrl": "https://media.prothomalo.com/prothomalo-bangla%2F2026-01-21%2Ff4m9wpea%2FWhatsApp-Image-2026-01-14-at-2.55.42-AM.jpeg?rect=0%2C0%2C1600%2C840&w=1200&ar=40%3A21&auto=format%2Ccompress&ogImage=true&mode=crop&overlay=https%3A%2F%2Fmedia.prothomalo.com%2Fprothomalo-bangla%2F2025-11-23%2F1558a7oz%2Fdefaultog.webp&overlay_position=bottom&overlay_width_pct=1",
            "body": "<html><body><div><div class=\"story-element story-element-text\"><div><p>টি–টুয়েন্টি বিশ্বকাপে না খেললেও বাংলাদেশকে কোনো ধরনের জরিমানা করবে না আইসিসি। এছাড়া ২০৩১ সালের ওয়ানডে বিশ্বকাপের আগেই আরও একটি বৈশ্বিক টুর্নামেন্টের স্বাগতিক করা হবে বাংলাদেশকে। আজ আইসিসির দেওয়া এক সংবাদ বিজ্ঞপ্তিতে এ কথা জানানো হয়েছে।</p><p>টি–টুয়েন্টি বিশ্বকাপে ভারতের বিপক্ষে পাকিস্তান ম্যাচ না খেলার সিদ্ধান্ত জানানোর পর গতকাল আইসিসির সঙ্গে পাকিস্তান ক্রিকেট বোর্ড ও বাংলাদেশ ক্রিকেট বোর্ডের সভা হয়। আজ রাতেই এক সংবাদ বিজ্ঞপ্তিতে বিসিবি সভাপতি আমিনুল ইসলাম জানান, ভারতের বিপক্ষে ম্যাচটি খেলতে পাকিস্তানকে অনুরোধ জানিয়েছেন তিনি। এরপরই আইসিসি বাংলাদেশকে নিয়ে হওয়া এসব সিদ্ধান্তের কথা জানাল।</p><p>বিস্তারিত আসছে</p></div></div></div></body></html>"
        },
        {
            "title": "জামায়াতের আমির বললেন এই নির্বাচন নতুন বাংলাদেশের পথে যাওয়ার মহাসুযোগ | প্রথম আলো",
            "time": "2026-02-09T17:38:42",
            "imgUrl": "https://media.prothomalo.com/prothomalo-bangla%2F2026-02-09%2F9b4ex1q2%2FWEB.jpg?rect=0%2C0%2C1920%2C1008&w=1200&ar=40%3A21&auto=format%2Ccompress&ogImage=true&mode=crop&overlay=https%3A%2F%2Fmedia.prothomalo.com%2Fprothomalo-bangla%2F2022-01%2F5a36c819-05a2-4bfb-ac50-57dd67355acb%2FBanner_7814X143.jpg&overlay_position=bottom&overlay_width_pct=1",
            "body": "<html><body><div><div class=\"story-title-info rG-CW\"><p><h1 data-title-0=\"জামায়াতের আমির বললেন এই নির্বাচন নতুন বাংলাদেশের পথে যাওয়ার মহাসুযোগ\" class=\"nA4h1 \">জামায়াতের আমির বললেন এই নির্বাচন নতুন বাংলাদেশের পথে যাওয়ার মহাসুযোগ</h1></p><div class=\"N8GaX\"><div class=\"XjL8O\"><div class=\"story-metadata-wrapper H6cQ5\"><p class=\"author-read-time-wrapper D-0u1\"></p><div class=\"time-social-share-wrapper _24WTx\"><p class=\"xuoYp\"><time datetime=\"2026-02-09T23:38:42+06:00\"><span>প্রকাশ: ০৯ ফেব্রুয়ারি ২০২৬, ১৭: ৩৮ </span></time></p></div></div></div></div></div></div></body></html>"
        },
        {
            "title": "যদি ভালো হন, চাঁদাবাজদের দল থেকে বের করে দেখান: তারেক রহমানকে সারজিস আলম | প্রথম আলো",
            "time": "2026-02-09T17:30:42",
            "imgUrl": "https://media.prothomalo.com/prothomalo-bangla%2F2026-02-09%2F0fiy26ky%2FWEB.jpg?rect=0%2C0%2C1920%2C1008&w=1200&ar=40%3A21&auto=format%2Ccompress&ogImage=true&mode=crop&overlay=https%3A%2F%2Fmedia.prothomalo.com%2Fprothomalo-bangla%2F2022-01%2F5a36c819-05a2-4bfb-ac50-57dd67355acb%2FBanner_7814X143.jpg&overlay_position=bottom&overlay_width_pct=1",
            "body": "<html><body><div><div class=\"story-title-info rG-CW\"><p><h1 data-title-0=\"যদি ভালো হন, চাঁদাবাজদের দল থেকে বের করে দেখান: তারেক রহমানকে সারজিস আলম \" class=\"nA4h1 \">যদি ভালো হন, চাঁদাবাজদের দল থেকে বের করে দেখান: তারেক রহমানকে সারজিস আলম </h1></p><div class=\"N8GaX\"><div class=\"XjL8O\"><div class=\"story-metadata-wrapper H6cQ5\"><p class=\"author-read-time-wrapper D-0u1\"></p><div class=\"time-social-share-wrapper _24WTx\"><p class=\"xuoYp\"><time datetime=\"2026-02-09T23:30:42+06:00\"><span>প্রকাশ: ০৯ ফেব্রুয়ারি ২০২৬, ১৭: ৩০ </span></time></p></div></div></div></div></div></div></body></html>"
        },
        {
            "title": "প্রথম ভোটারদের জন্য ভোটকেন্দ্র কতটা প্রস্তুত | ওয়ালটন ফ্যান নির্বাচনী হাওয়া | পর্ব-৯ | প্রথম আলো",
            "time": "2026-02-09T17:21:46",
            "imgUrl": "https://media.prothomalo.com/prothomalo-bangla%2F2026-02-09%2F2lgwqrvi%2FWEB.jpg?rect=0%2C0%2C800%2C420&w=1200&ar=40%3A21&auto=format%2Ccompress&ogImage=true&mode=crop&overlay=https%3A%2F%2Fmedia.prothomalo.com%2Fprothomalo-bangla%2F2022-01%2F5a36c819-05a2-4bfb-ac50-57dd67355acb%2FBanner_7814X143.jpg&overlay_position=bottom&overlay_width_pct=1",
            "body": "<html><body><div><div class=\"story-title-info rG-CW\"><p><h1 data-title-0=\"প্রথম ভোটারদের জন্য ভোটকেন্দ্র কতটা প্রস্তুত | ওয়ালটন ফ্যান নির্বাচনী হাওয়া | পর্ব–৯\" class=\"nA4h1 \">প্রথম ভোটারদের জন্য ভোটকেন্দ্র কতটা প্রস্তুত | ওয়ালটন ফ্যান নির্বাচনী হাওয়া | পর্ব–৯</h1></p><div class=\"N8GaX\"><div class=\"XjL8O\"><div class=\"story-metadata-wrapper H6cQ5\"><p class=\"author-read-time-wrapper D-0u1\"></p><div class=\"time-social-share-wrapper _24WTx\"><p class=\"xuoYp\"><time datetime=\"2026-02-09T23:21:46+06:00\"><span>প্রকাশ: ০৯ ফেব্রুয়ারি ২০২৬, ১৭: ২১ </span></time></p></div></div></div></div></div></div></body></html>"
        },
        {
            "title": "পরবর্তী এমপির কাছে একটাই দাবি, চাঁদাবাজি বন্ধ হোক | প্রথম আলো",
            "time": "2026-02-09T17:14:09",
            "imgUrl": "https://media.prothomalo.com/prothomalo-bangla%2F2026-02-09%2Ft4tefdvu%2FWEB.jpg?rect=0%2C0%2C800%2C420&w=1200&ar=40%3A21&auto=format%2Ccompress&ogImage=true&mode=crop&overlay=https%3A%2F%2Fmedia.prothomalo.com%2Fprothomalo-bangla%2F2022-01%2F5a36c819-05a2-4bfb-ac50-57dd67355acb%2FBanner_7814X143.jpg&overlay_position=bottom&overlay_width_pct=1",
            "body": "<html><body><div><div class=\"story-title-info rG-CW\"><p><h1 data-title-0=\"পরবর্তী এমপির কাছে একটাই দাবি, চাঁদাবাজি বন্ধ হোক\" class=\"nA4h1 \">পরবর্তী এমপির কাছে একটাই দাবি, চাঁদাবাজি বন্ধ হোক</h1></p><div class=\"N8GaX\"><div class=\"XjL8O\"><div class=\"story-metadata-wrapper H6cQ5\"><p class=\"author-read-time-wrapper D-0u1\"></p><div class=\"time-social-share-wrapper _24WTx\"><p class=\"xuoYp\"><time datetime=\"2026-02-09T23:14:09+06:00\"><span>প্রকাশ: ০৯ ফেব্রুয়ারি ২০২৬, ১৭: ১৪ </span></time></p></div></div></div></div></div></div></body></html>"
        },
        {
            "title": "নির্বাচনকে প্রভাবিত করতে নানান কলাকৌশল চলছে: জোনায়েদ সাকি | প্রথম আলো",
            "time": "2026-02-09T17:08:15",
            "imgUrl": "https://media.prothomalo.com/prothomalo-bangla%2F2026-02-09%2F0jjli1t8%2FBBariaDH051720260209WhatsApp-Image-2026-02-09-at-8.59.36-PM.jpg?rect=0%2C182%2C1600%2C840&w=1200&ar=40%3A21&auto=format%2Ccompress&ogImage=true&mode=crop&overlay=https%3A%2F%2Fmedia.prothomalo.com%2Fprothomalo-bangla%2F2024-08-31%2F1m4oa2xi%2FBanner_7814X143.jpg&overlay_position=bottom&overlay_width_pct=1",
            "body": "<html><body><div><div class=\"story-element story-element-text\"><div><p>ব্রাহ্মণবাড়িয়া-৬ (বাঞ্ছারামপুর) আসনে বিএনপি সমর্থিত প্রার্থী ও গণসংহতি আন্দোলনের প্রধান সমন্বয়ক জোনায়েদ সাকি বলেন, ‘নির্বাচন আমাদের অস্তিত্ব ও বিকাশের জন্য জরুরি। নির্বাচনকে প্রভাবিত করতে নানান কলাকৌশল চলছে। কিন্তু সুষ্ঠু, অবাধ ও গ্রহণযোগ্য নির্বাচন চাই, এটা হতেই হবে। ইলেকশন ইঞ্জিনিয়ারিংসহ নানা কথা শোনা যাচ্ছে। এসব তৎপরতা থেকে সবাইকে বিরত থাকতে হবে।’</p><p>সোমবার রাত সোয়া আটটার দিকে বাঞ্ছারামপুর উপজেলার রূপসদী ইউনিয়নের নির্বাচনী জনসভায় এ কথা বলেন জোনায়েদ সাকি। শেষ দিনের নির্বাচনী প্রচারণায় ব্যস্ত সময় পার করেন জোনায়েদ সাকি। এদিন বেলা তিনটা থেকে উপজেলার ১৩টি ইউনিয়ন ও বাঞ্ছারামপুর পৌরসভায় একযোগে মাথাল মার্কার পক্ষে গণমিছিল হয়।</p></div></div></div></body></html>"
        },
        {
            "title": "সিলেটে প্রচারের শেষ দিনে প্রার্থীদের প্রতিশ্রুতির ফুলঝুরি | প্রথম আলো",
            "time": "2026-02-09T17:07:01",
            "imgUrl": "https://media.prothomalo.com/prothomalo-bangla%2F2026-02-09%2Fvqnxq0sy%2FSylhetDH048620260209Sylhet-election-Pic-2.jpg?rect=0%2C0%2C4032%2C2117&w=1200&ar=40%3A21&auto=format%2Ccompress&ogImage=true&mode=crop&overlay=https%3A%2F%2Fmedia.prothomalo.com%2Fprothomalo-bangla%2F2024-08-31%2F1m4oa2xi%2FBanner_7814X143.jpg&overlay_position=bottom&overlay_width_pct=1",
            "body": "<html><body><div><div class=\"story-element story-element-text\"><div><p>বিকেলে গোয়াইনঘাট উপজেলা সদরের কেন্দ্রীয় শহীদ মিনারের সামনে বিএনপি প্রার্থী আরিফুল হক চৌধুরীর নির্বাচনী জনসভা অনুষ্ঠিত হয়। এ সময় প্রধান অতিথির বক্তব্যে তিনি বলেন, ‘গোয়াইনঘাট, কোম্পানীগঞ্জ ও জৈন্তাপুর উপজেলার প্রতিটি ইউনিয়নে গিয়ে মানুষের যে ভালোবাসা আমি পেয়েছি, তারা যেভাবে আপন করে নিয়েছেন, তা অভূতপূর্ব। এখন কাজের মাধ্যমেই আমি তাঁদের ভালোবাসার প্রতিদান দেব।’</p><p>গোয়াইনঘাট উপজেলা বিএনপির সভাপতি মাহবুব আলমের সভাপতিত্বে ও সাধারণ সম্পাদক মো. জসিম উদ্দিনের সঞ্চালনায় সভা হয়। এতে বিশেষ অতিথির বক্তব্য দেন গোয়াইনঘাট উপজেলা পরিষদের সাবেক চেয়ারম্যান আবদুল হাকিম চৌধুরী, সিলেট মহানগর বিএনপির সাবেক সাধারণ সম্পাদক বদরুজ্জামান সেলিম, জমিয়তে উলামায়ে ইসলাম বাংলাদেশ সিলেট জেলার সভাপতি মাওলানা আতাউর রহমান প্রমুখ।</p><p>আরিফুল হক চৌধুরী বক্তব্যে সিলেট-৪ আসনের উন্নয়নে বিভিন্ন প্রতিশ্রুতি দেন। তিনি বলেন, ‘এ অঞ্চলের মানুষের দীর্ঘদিনের দাবি সনাতন পদ্ধতিতে পাথর কোয়ারি খুলে দেওয়া, প্রতিটি নাগরিকের জন্য নিরবচ্ছিন্ন বিদ্যুৎ, ইন্টারনেট, কৃষি যন্ত্রপাতি, বিশুদ্ধ খাবার পানি, আধুনিক স্বাস্থ্যসেবা নিশ্চিত করা হবে আমার প্রধান কাজ।’</p></div></div></div></body></html>"
        },
        {
            "title": "ভোটকেন্দ্রে মুঠোফোন ব্যবহার ও নির্বাচনী এলাকায় বহিরাগতদের অবস্থান প্রসঙ্গে ইসি | প্রথম আলো",
            "time": "2026-02-09T17:06:07",
            "imgUrl": "https://media.prothomalo.com/prothomalo-bangla%2F2026-02-09%2Fj7k18qk4%2FAudioThumbnail-Copy-Copy.jpg?rect=0%2C0%2C1920%2C1008&w=1200&ar=40%3A21&auto=format%2Ccompress&ogImage=true&mode=crop&overlay=https%3A%2F%2Fmedia.prothomalo.com%2Fprothomalo-bangla%2F2022-01%2F5a36c819-05a2-4bfb-ac50-57dd67355acb%2FBanner_7814X143.jpg&overlay_position=bottom&overlay_width_pct=1",
            "body": "<html><body><div><div class=\"story-title-info rG-CW\"><p class=\"print-entity-section-wrapper ut4Ac\"><h2 class=\"_-94Px\">অডিও সংবাদ </h2></p><p><h1 data-title-0=\"ভোটকেন্দ্রে মুঠোফোন ব্যবহার ও নির্বাচনী এলাকায় বহিরাগতদের অবস্থান প্রসঙ্গে ইসি\" class=\"nA4h1 \">ভোটকেন্দ্রে মুঠোফোন ব্যবহার ও নির্বাচনী এলাকায় বহিরাগতদের অবস্থান প্রসঙ্গে ইসি</h1></p><div class=\"N8GaX\"><div class=\"XjL8O\"><div class=\"story-metadata-wrapper H6cQ5\"><p class=\"author-read-time-wrapper D-0u1\"></p><div class=\"time-social-share-wrapper _24WTx\"><p class=\"xuoYp\"><time datetime=\"2026-02-09T23:06:07+06:00\"><span>প্রকাশ: ০৯ ফেব্রুয়ারি ২০২৬, ১৭: ০৬ </span></time></p></div></div></div></div></div></div></body></html>"
        },
        {
            "title": "বিবেক-বুদ্ধি অনুযায়ী সঠিক প্রতিনিধি নির্বাচন করুন: সিপিবি সভাপতি | প্রথম আলো",
            "time": "2026-02-09T17:05:56",
            "imgUrl": "https://media.prothomalo.com/prothomalo-bangla%2F2026-02-09%2Fjsxg4fd5%2FUntitled-5.png?rect=0%2C0%2C1920%2C1008&w=1200&ar=40%3A21&auto=format%2Ccompress&ogImage=true&mode=crop&overlay=https%3A%2F%2Fmedia.prothomalo.com%2Fprothomalo-bangla%2F2022-01%2F5a36c819-05a2-4bfb-ac50-57dd67355acb%2FBanner_7814X143.jpg&overlay_position=bottom&overlay_width_pct=1",
            "body": "<html><body><div><div class=\"story-element story-element-text\"><div><p>ভাষণে সিপিবি সভাপতি বলেন, রাষ্ট্র ও সমাজ গভীর ও বহুমাত্রিক সংকটের মধ্য দিয়ে যাচ্ছে। গণতন্ত্রের অবক্ষয়, আইনের শাসনের দুর্বলতা, মতপ্রকাশের স্বাধীনতায় হস্তক্ষেপ, চরম অর্থনৈতিক বৈষম্য ও সাধারণ মানুষের জীবনমানের অবনতি মিলিয়ে বাংলাদেশ আজ একটি গুরুতর সন্ধিক্ষণে দাঁড়িয়ে আছে।</p><p>বক্তব্যে ১৯৭১ সালের মহান মুক্তিযুদ্ধের চেতনার কথা উল্লেখ করে কাজী সাজ্জাদ জহির চন্দন বলেন, মুক্তিযুদ্ধের লক্ষ্য ছিল একটি গণতান্ত্রিক, সাম্যভিত্তিক ও মানবিক রাষ্ট্র গড়ে তোলা। কিন্তু স্বাধীনতার দীর্ঘ পথচলায় সেই লক্ষ্য এখনো পূরণ হয়নি। এর ফল হিসেবে সাধারণ মানুষ নিরাপত্তাহীনতা, বৈষম্য ও অনিশ্চয়তার মধ্যে দিন কাটাচ্ছে।</p><p>সিপিবি সভাপতির বক্তব্যে জুলাই গণ-অভ্যুত্থানের প্রসঙ্গও উঠে আসে। তিনি বলেন, দীর্ঘদিনের দমন–পীড়ন, বৈষম্য ও ফ্যাসিবাদী শাসনের বিরুদ্ধে ছাত্র-জনতার ধারাবাহিক আন্দোলনের একটি গুরুত্বপূর্ণ অধ্যায় ছিল এই গণ-অভ্যুত্থান। এতে সহস্রাধিক মানুষের প্রাণহানির কথা উল্লেখ করে তিনি নিহত ব্যক্তিদের হত্যাকাণ্ডের বিচার দাবি করেন।</p></div></div></div></body></html>"
        },
        {
            "title": "কলা দিয়ে বানান কাস্টার্ড পুডিং, জেনে নিন রেসিপি | প্রথম আলো",
            "time": "2026-02-09T17:04:46",
            "imgUrl": "https://media.prothomalo.com/prothomalo-bangla%2F2026-02-09%2Fl06oik6w%2F200206khaled-Sarker0011.jpg?rect=0%2C284%2C4000%2C2100&w=1200&ar=40%3A21&auto=format%2Ccompress&ogImage=true&mode=crop&overlay=https%3A%2F%2Fmedia.prothomalo.com%2Fprothomalo-bangla%2F2025-11-23%2F1558a7oz%2Fdefaultog.webp&overlay_position=bottom&overlay_width_pct=1",
            "body": "<html><body><div><div class=\"story-page-hero RJoJJ\"><p class=\"cdKYX\"><figcaption class=\"story-element-image-caption custom-gallery-image\">কলার কাস্টার্ড পুডিং<span class=\"custom-gallery-image _3bj2K SZnJd\">ছবি: খালেদ সরকার</span></figcaption></p></div></div></body></html>"
        },
        {
            "title": "পাকিস্তানকে ভারতের বিপক্ষে খেলতে অনুরোধ জানিয়েছেন বিসিবি সভাপতি আমিনুল | প্রথম আলো",
            "time": "2026-02-09T17:02:45",
            "imgUrl": "https://media.prothomalo.com/prothomalo-bangla%2F2026-02-09%2Fx2m4pvvi%2FHApb-sjaYAEvTcI.jpg?rect=0%2C0%2C1303%2C684&w=1200&ar=40%3A21&auto=format%2Ccompress&ogImage=true&mode=crop&overlay=https%3A%2F%2Fmedia.prothomalo.com%2Fprothomalo-bangla%2F2025-11-23%2F1558a7oz%2Fdefaultog.webp&overlay_position=bottom&overlay_width_pct=1",
            "body": "<html><body><div><div class=\"story-element story-element-text\"><div><p>বিশ্ব ক্রিকেটের জন্যই গুরুত্বপূর্ণ এই ম্যাচটি যেন পাকিস্তান খেলে, এ নিয়ে আলোচনা করতে গতকাল পাকিস্তান যান আইসিসির প্রতিনিধিরা। সেই বৈঠকে ছিলেন বিসিবি সভাপতি আমিনুল ইসলামও।</p><p>বিসিবি সভাপতিকে উদ্ধৃত করে সংবাদ বিজ্ঞপ্তিতে লেখা হয়েছে, ‘গতকাল পাকিস্তানে আমার সংক্ষিপ্ত সফর এবং আমাদের আলোচনার সম্ভাব্য ফলাফলের প্রেক্ষিতে, পুরো ক্রিকেট ইকোসিস্টেমের স্বার্থে ১৫ ফেব্রুয়ারি ভারতের বিপক্ষে নির্ধারিত আইসিসি টি-টোয়েন্টি বিশ্বকাপ ম্যাচটি খেলার জন্য আমি পাকিস্তানের প্রতি অনুরোধ জানাচ্ছি।’</p></div></div></div></body></html>"
        },
        {
            "title": "জামায়াত ক্ষমতায় গেলে দলের সরকার হবে না, একটিবার সুযোগ দিন : শফিকুর রহমান | প্রথম আলো",
            "time": "2026-02-09T17:01:15",
            "imgUrl": "https://media.prothomalo.com/prothomalo-bangla%2F2026-02-09%2Fm51t2k3c%2FWhatsApp-Image-2026-02-09-at-10.53.23-PM.jpeg?rect=0%2C0%2C1600%2C840&w=1200&ar=40%3A21&auto=format%2Ccompress&ogImage=true&mode=crop&overlay=https%3A%2F%2Fmedia.prothomalo.com%2Fprothomalo-bangla%2F2024-08-31%2F1m4oa2xi%2FBanner_7814X143.jpg&overlay_position=bottom&overlay_width_pct=1",
            "body": "<html><body><div><div class=\"story-element story-element-text\"><div><p>শফিকুর রহমান আরও বলেন, ‘দোহার ও নবাবগঞ্জের অসংখ্য মানুষ বিদেশে থাকেন। প্রবাসীরা যাতে সেখানে মারা গেলে লাশ পড়ে না থাকে, সেই ব্যবস্থা নেওয়া হবে। সব ধর্মের মানুষের প্রতি ন্যায় ও ইনসাফ প্রতিষ্ঠা করা হবে।’</p><p>জনসভায় দাঁড়িপাল্লার প্রার্থী নজরুল ইসলামকে হাত ধরে পরিচয় করিয়ে দেন জামায়াতের আমির। জনসভায় উপস্থিত যুবকদের উদ্দেশে তিনি বলেন, ‘আগামীর বাংলাদেশ তরুণ–যুবকের বাংলাদেশ। দাঁড়িপাল্লার প্রার্থীকে তোমাদের হাতে তুলে দিয়ে গেলাম, তোমরাই তাঁকে বিজয়ী করবে।’</p></div></div></div></body></html>"
        },
        {
            "title": "যেভাবে বানাবেন কেশর আলুর ডিলাইট, দেখুন রেসিপি | প্রথম আলো",
            "time": "2026-02-09T16:59:59",
            "imgUrl": "https://media.prothomalo.com/prothomalo-bangla%2F2026-02-09%2Flxisxiez%2F200206khaled-Sarker0022.jpg?rect=0%2C284%2C4000%2C2100&w=1200&ar=40%3A21&auto=format%2Ccompress&ogImage=true&mode=crop&overlay=https%3A%2F%2Fmedia.prothomalo.com%2Fprothomalo-bangla%2F2025-11-23%2F1558a7oz%2Fdefaultog.webp&overlay_position=bottom&overlay_width_pct=1",
            "body": "<html><body><div><div class=\"story-page-hero RJoJJ\"><p class=\"cdKYX\"><figcaption class=\"story-element-image-caption custom-gallery-image\">কেশর আলুর ডিলাইট<span class=\"custom-gallery-image _3bj2K SZnJd\">ছবি: খালেদ সরকার</span></figcaption></p></div></div></body></html>"
        }
    ]
}